{
	"parent": "block/block",
	"render_type": "minecraft:cutout",
	"textures": {
		"0": "wizards_reborn:block/steam_thermal_storage",
		"1": "wizards_reborn:block/steam_thermal_storage_ring",
		"particle": "wizards_reborn:block/alchemy_block"
	},
	"elements": [
		{
			"from": [4, 13, 4],
			"to": [12, 15, 12],
			"faces": {
				"north": {"uv": [0, 0, 8, 2], "texture": "#0"},
				"east": {"uv": [0, 0, 8, 2], "texture": "#0"},
				"south": {"uv": [0, 0, 8, 2], "texture": "#0"},
				"west": {"uv": [0, 0, 8, 2], "texture": "#0"},
				"up": {"uv": [8, 0, 16, 8], "texture": "#0"},
				"down": {"uv": [8, 0, 16, 8], "texture": "#0"}
			}
		},
		{
			"from": [4, 1, 4],
			"to": [12, 3, 12],
			"faces": {
				"north": {"uv": [0, 12, 8, 14], "texture": "#0"},
				"east": {"uv": [0, 12, 8, 14], "texture": "#0"},
				"south": {"uv": [0, 12, 8, 14], "texture": "#0"},
				"west": {"uv": [0, 12, 8, 14], "texture": "#0"},
				"up": {"uv": [8, 0, 16, 8], "texture": "#0"},
				"down": {"uv": [8, 0, 16, 8], "texture": "#0"}
			}
		},
		{
			"from": [4, 3, 4],
			"to": [12, 13, 5],
			"faces": {
				"north": {"uv": [0, 2, 8, 12], "texture": "#0"},
				"east": {"uv": [7, 2, 8, 12], "texture": "#0"},
				"south": {"uv": [0, 2, 8, 12], "texture": "#0"},
				"west": {"uv": [0, 2, 1, 12], "texture": "#0"},
				"up": {"uv": [0, 2, 8, 3], "texture": "#0"},
				"down": {"uv": [0, 11, 8, 12], "texture": "#0"}
			}
		},
		{
			"from": [4, 3, 11],
			"to": [12, 13, 12],
			"faces": {
				"north": {"uv": [0, 2, 8, 12], "texture": "#0"},
				"east": {"uv": [0, 2, 1, 12], "texture": "#0"},
				"south": {"uv": [0, 2, 8, 12], "texture": "#0"},
				"west": {"uv": [7, 2, 8, 12], "texture": "#0"},
				"up": {"uv": [0, 2, 8, 3], "texture": "#0"},
				"down": {"uv": [0, 11, 8, 12], "texture": "#0"}
			}
		},
		{
			"from": [11, 3, 5],
			"to": [12, 13, 11],
			"faces": {
				"north": {"uv": [6, 2, 7, 12], "texture": "#0"},
				"east": {"uv": [1, 2, 7, 12], "texture": "#0"},
				"south": {"uv": [1, 2, 2, 12], "texture": "#0"},
				"west": {"uv": [1, 2, 7, 12], "texture": "#0"},
				"up": {"uv": [1, 2, 7, 3], "rotation": 270, "texture": "#0"},
				"down": {"uv": [1, 11, 7, 12], "rotation": 90, "texture": "#0"}
			}
		},
		{
			"from": [4, 3, 5],
			"to": [5, 13, 11],
			"faces": {
				"north": {"uv": [6, 2, 7, 12], "texture": "#0"},
				"east": {"uv": [1, 2, 7, 12], "texture": "#0"},
				"south": {"uv": [1, 2, 2, 12], "texture": "#0"},
				"west": {"uv": [1, 2, 7, 12], "texture": "#0"},
				"up": {"uv": [1, 2, 7, 3], "rotation": 270, "texture": "#0"},
				"down": {"uv": [1, 11, 7, 12], "rotation": 90, "texture": "#0"}
			}
		},
		{
			"from": [6, 15, 6],
			"to": [10, 16, 10],
			"faces": {
				"north": {"uv": [10, 2, 14, 3], "texture": "#0"},
				"east": {"uv": [10, 2, 14, 3], "texture": "#0"},
				"south": {"uv": [10, 2, 14, 3], "texture": "#0"},
				"west": {"uv": [10, 2, 14, 3], "texture": "#0"},
				"up": {"uv": [10, 2, 14, 6], "texture": "#0"},
				"down": {"uv": [10, 2, 14, 6], "texture": "#0"}
			}
		},
		{
			"from": [6, 0, 6],
			"to": [10, 1, 10],
			"faces": {
				"north": {"uv": [10, 2, 14, 3], "texture": "#0"},
				"east": {"uv": [10, 2, 14, 3], "texture": "#0"},
				"south": {"uv": [10, 2, 14, 3], "texture": "#0"},
				"west": {"uv": [10, 2, 14, 3], "texture": "#0"},
				"up": {"uv": [10, 2, 14, 6], "texture": "#0"},
				"down": {"uv": [10, 2, 14, 6], "texture": "#0"}
			}
		},
		{
			"from": [3, 2, 3],
			"to": [13, 4, 13],
			"faces": {
				"north": {"uv": [0, 10, 10, 12], "texture": "#1"},
				"east": {"uv": [0, 10, 10, 12], "texture": "#1"},
				"south": {"uv": [0, 10, 10, 12], "texture": "#1"},
				"west": {"uv": [0, 10, 10, 12], "texture": "#1"},
				"up": {"uv": [0, 0, 10, 10], "texture": "#1"},
				"down": {"uv": [0, 0, 10, 10], "texture": "#1"}
			}
		},
		{
			"from": [3, 12, 3],
			"to": [13, 14, 13],
			"faces": {
				"north": {"uv": [0, 10, 10, 12], "texture": "#1"},
				"east": {"uv": [0, 10, 10, 12], "texture": "#1"},
				"south": {"uv": [0, 10, 10, 12], "texture": "#1"},
				"west": {"uv": [0, 10, 10, 12], "texture": "#1"},
				"up": {"uv": [0, 0, 10, 10], "texture": "#1"},
				"down": {"uv": [0, 0, 10, 10], "texture": "#1"}
			}
		}
	],
	"groups": [
		{
			"name": "group",
			"origin": [0, 0, 0],
			"color": 0,
			"children": [0, 1, 2, 3, 4, 5]
		},
		6,
		7,
		8,
		9
	]
}